./README.md
./pyproject.toml
./stt/__init__.py
./stt/stt.py
./tests/test_stt.py
getstream_plugins_moonshine-0.1.1.dist-info/METADATA
getstream_plugins_moonshine-0.1.1.dist-info/WHEEL
getstream_plugins_moonshine-0.1.1.dist-info/RECORD
