Metadata-Version: 2.4
Name: getstream-plugins-moonshine
Version: 0.1.1
Summary: Moonshine plugin for GetStream
License-Expression: MIT
Requires-Python: >=3.10
Requires-Dist: getstream-plugins-common>=0.1.1
Requires-Dist: getstream[webrtc]>=2.3.0a4
Requires-Dist: numpy<2.3,>=2.2.6
Requires-Dist: onnxruntime>=1.22.0
Requires-Dist: soundfile>=0.13.1
